{
  "hits": {
    "random_forest": [
      "streak_type_hot",
      "streak_type_cold",
      "streak_count",
      "hit_streak",
      "win_streak",
      "rolling_result_avg_7",
      "d7_hits",
      "d7_home_runs",
      "d7_rbis",
      "d7_walks",
      "d15_hits",
      "d15_home_runs",
      "d15_rbis",
      "d15_walks",
      "d30_hits",
      "d30_home_runs",
      "d30_rbis",
      "d30_walks",
      "d7_total_bases",
      "d15_total_bases",
      "d30_total_bases",
      "d7_hits_runs_rbis",
      "d15_hits_runs_rbis",
      "d30_hits_runs_rbis",
      "d7_stolen_bases",
      "d15_stolen_bases",
      "d30_stolen_bases",
      "d7_strikeouts_batting",
      "d15_strikeouts_batting",
      "d30_strikeouts_batting",
      "d7_strikeouts_pitching",
      "d15_strikeouts_pitching",
      "d30_strikeouts_pitching",
      "d7_walks_allowed",
      "d15_walks_allowed",
      "d30_walks_allowed",
      "d7_earned_runs",
      "d15_earned_runs",
      "d30_earned_runs",
      "d7_hits_allowed",
      "d15_hits_allowed",
      "d30_hits_allowed",
      "bvp_at_bats",
      "bvp_hits",
      "bvp_home_runs",
      "bvp_rbi",
      "bvp_strikeouts",
      "bvp_walks",
      "bvp_plate_appearances",
      "line",
      "line_diff"
    ],
    "logistic_regression": [
      "streak_type_hot",
      "streak_type_cold",
      "streak_count",
      "hit_streak",
      "win_streak",
      "rolling_result_avg_7",
      "d7_hits",
      "d7_home_runs",
      "d7_rbis",
      "d7_walks",
      "d15_hits",
      "d15_home_runs",
      "d15_rbis",
      "d15_walks",
      "d30_hits",
      "d30_home_runs",
      "d30_rbis",
      "d30_walks",
      "d7_total_bases",
      "d15_total_bases",
      "d30_total_bases",
      "d7_hits_runs_rbis",
      "d15_hits_runs_rbis",
      "d30_hits_runs_rbis",
      "d7_stolen_bases",
      "d15_stolen_bases",
      "d30_stolen_bases",
      "d7_strikeouts_batting",
      "d15_strikeouts_batting",
      "d30_strikeouts_batting",
      "d7_strikeouts_pitching",
      "d15_strikeouts_pitching",
      "d30_strikeouts_pitching",
      "d7_walks_allowed",
      "d15_walks_allowed",
      "d30_walks_allowed",
      "d7_earned_runs",
      "d15_earned_runs",
      "d30_earned_runs",
      "d7_hits_allowed",
      "d15_hits_allowed",
      "d30_hits_allowed",
      "bvp_at_bats",
      "bvp_hits",
      "bvp_home_runs",
      "bvp_rbi",
      "bvp_strikeouts",
      "bvp_walks",
      "bvp_plate_appearances",
      "line",
      "line_diff"
    ]
  },
  "singles": {
    "random_forest": [
      "streak_type_hot",
      "streak_type_cold",
      "streak_count",
      "hit_streak",
      "win_streak",
      "rolling_result_avg_7",
      "d7_hits",
      "d7_home_runs",
      "d7_rbis",
      "d7_walks",
      "d15_hits",
      "d15_home_runs",
      "d15_rbis",
      "d15_walks",
      "d30_hits",
      "d30_home_runs",
      "d30_rbis",
      "d30_walks",
      "d7_total_bases",
      "d15_total_bases",
      "d30_total_bases",
      "d7_hits_runs_rbis",
      "d15_hits_runs_rbis",
      "d30_hits_runs_rbis",
      "d7_stolen_bases",
      "d15_stolen_bases",
      "d30_stolen_bases",
      "d7_strikeouts_batting",
      "d15_strikeouts_batting",
      "d30_strikeouts_batting",
      "d7_strikeouts_pitching",
      "d15_strikeouts_pitching",
      "d30_strikeouts_pitching",
      "d7_walks_allowed",
      "d15_walks_allowed",
      "d30_walks_allowed",
      "d7_earned_runs",
      "d15_earned_runs",
      "d30_earned_runs",
      "d7_hits_allowed",
      "d15_hits_allowed",
      "d30_hits_allowed",
      "bvp_at_bats",
      "bvp_hits",
      "bvp_home_runs",
      "bvp_rbi",
      "bvp_strikeouts",
      "bvp_walks",
      "bvp_plate_appearances",
      "line",
      "line_diff"
    ],
    "logistic_regression": [
      "streak_type_hot",
      "streak_type_cold",
      "streak_count",
      "hit_streak",
      "win_streak",
      "rolling_result_avg_7",
      "d7_hits",
      "d7_home_runs",
      "d7_rbis",
      "d7_walks",
      "d15_hits",
      "d15_home_runs",
      "d15_rbis",
      "d15_walks",
      "d30_hits",
      "d30_home_runs",
      "d30_rbis",
      "d30_walks",
      "d7_total_bases",
      "d15_total_bases",
      "d30_total_bases",
      "d7_hits_runs_rbis",
      "d15_hits_runs_rbis",
      "d30_hits_runs_rbis",
      "d7_stolen_bases",
      "d15_stolen_bases",
      "d30_stolen_bases",
      "d7_strikeouts_batting",
      "d15_strikeouts_batting",
      "d30_strikeouts_batting",
      "d7_strikeouts_pitching",
      "d15_strikeouts_pitching",
      "d30_strikeouts_pitching",
      "d7_walks_allowed",
      "d15_walks_allowed",
      "d30_walks_allowed",
      "d7_earned_runs",
      "d15_earned_runs",
      "d30_earned_runs",
      "d7_hits_allowed",
      "d15_hits_allowed",
      "d30_hits_allowed",
      "bvp_at_bats",
      "bvp_hits",
      "bvp_home_runs",
      "bvp_rbi",
      "bvp_strikeouts",
      "bvp_walks",
      "bvp_plate_appearances",
      "line",
      "line_diff"
    ]
  },
  "doubles": {
    "random_forest": [
      "streak_type_hot",
      "streak_type_cold",
      "streak_count",
      "hit_streak",
      "win_streak",
      "rolling_result_avg_7",
      "d7_hits",
      "d7_home_runs",
      "d7_rbis",
      "d7_walks",
      "d15_hits",
      "d15_home_runs",
      "d15_rbis",
      "d15_walks",
      "d30_hits",
      "d30_home_runs",
      "d30_rbis",
      "d30_walks",
      "d7_total_bases",
      "d15_total_bases",
      "d30_total_bases",
      "d7_hits_runs_rbis",
      "d15_hits_runs_rbis",
      "d30_hits_runs_rbis",
      "d7_stolen_bases",
      "d15_stolen_bases",
      "d30_stolen_bases",
      "d7_strikeouts_batting",
      "d15_strikeouts_batting",
      "d30_strikeouts_batting",
      "d7_strikeouts_pitching",
      "d15_strikeouts_pitching",
      "d30_strikeouts_pitching",
      "d7_walks_allowed",
      "d15_walks_allowed",
      "d30_walks_allowed",
      "d7_earned_runs",
      "d15_earned_runs",
      "d30_earned_runs",
      "d7_hits_allowed",
      "d15_hits_allowed",
      "d30_hits_allowed",
      "bvp_at_bats",
      "bvp_hits",
      "bvp_home_runs",
      "bvp_rbi",
      "bvp_strikeouts",
      "bvp_walks",
      "bvp_plate_appearances",
      "line_diff"
    ],
    "logistic_regression": [
      "streak_type_hot",
      "streak_type_cold",
      "streak_count",
      "hit_streak",
      "win_streak",
      "rolling_result_avg_7",
      "d7_hits",
      "d7_home_runs",
      "d7_rbis",
      "d7_walks",
      "d15_hits",
      "d15_home_runs",
      "d15_rbis",
      "d15_walks",
      "d30_hits",
      "d30_home_runs",
      "d30_rbis",
      "d30_walks",
      "d7_total_bases",
      "d15_total_bases",
      "d30_total_bases",
      "d7_hits_runs_rbis",
      "d15_hits_runs_rbis",
      "d30_hits_runs_rbis",
      "d7_stolen_bases",
      "d15_stolen_bases",
      "d30_stolen_bases",
      "d7_strikeouts_batting",
      "d15_strikeouts_batting",
      "d30_strikeouts_batting",
      "d7_strikeouts_pitching",
      "d15_strikeouts_pitching",
      "d30_strikeouts_pitching",
      "d7_walks_allowed",
      "d15_walks_allowed",
      "d30_walks_allowed",
      "d7_earned_runs",
      "d15_earned_runs",
      "d30_earned_runs",
      "d7_hits_allowed",
      "d15_hits_allowed",
      "d30_hits_allowed",
      "bvp_at_bats",
      "bvp_hits",
      "bvp_home_runs",
      "bvp_rbi",
      "bvp_strikeouts",
      "bvp_walks",
      "bvp_plate_appearances",
      "line_diff"
    ]
  },
  "triples": {
    "random_forest": [
      "streak_type_hot",
      "streak_count",
      "hit_streak",
      "win_streak",
      "rolling_result_avg_7",
      "d7_hits",
      "d7_home_runs",
      "d7_rbis",
      "d7_walks",
      "d15_hits",
      "d15_home_runs",
      "d15_rbis",
      "d15_walks",
      "d30_hits",
      "d30_home_runs",
      "d30_rbis",
      "d30_walks",
      "d7_total_bases",
      "d15_total_bases",
      "d30_total_bases",
      "d7_hits_runs_rbis",
      "d15_hits_runs_rbis",
      "d30_hits_runs_rbis",
      "d7_stolen_bases",
      "d15_stolen_bases",
      "d30_stolen_bases",
      "d7_strikeouts_batting",
      "d15_strikeouts_batting",
      "d30_strikeouts_batting",
      "d7_strikeouts_pitching",
      "d15_strikeouts_pitching",
      "d30_strikeouts_pitching",
      "d7_walks_allowed",
      "d15_walks_allowed",
      "d30_walks_allowed",
      "d7_earned_runs",
      "d15_earned_runs",
      "d30_earned_runs",
      "d7_hits_allowed",
      "d15_hits_allowed",
      "d30_hits_allowed",
      "bvp_at_bats",
      "bvp_hits",
      "bvp_home_runs",
      "bvp_rbi",
      "bvp_strikeouts",
      "bvp_walks",
      "bvp_plate_appearances",
      "line",
      "line_diff"
    ],
    "logistic_regression": [
      "streak_type_hot",
      "streak_count",
      "hit_streak",
      "win_streak",
      "rolling_result_avg_7",
      "d7_hits",
      "d7_home_runs",
      "d7_rbis",
      "d7_walks",
      "d15_hits",
      "d15_home_runs",
      "d15_rbis",
      "d15_walks",
      "d30_hits",
      "d30_home_runs",
      "d30_rbis",
      "d30_walks",
      "d7_total_bases",
      "d15_total_bases",
      "d30_total_bases",
      "d7_hits_runs_rbis",
      "d15_hits_runs_rbis",
      "d30_hits_runs_rbis",
      "d7_stolen_bases",
      "d15_stolen_bases",
      "d30_stolen_bases",
      "d7_strikeouts_batting",
      "d15_strikeouts_batting",
      "d30_strikeouts_batting",
      "d7_strikeouts_pitching",
      "d15_strikeouts_pitching",
      "d30_strikeouts_pitching",
      "d7_walks_allowed",
      "d15_walks_allowed",
      "d30_walks_allowed",
      "d7_earned_runs",
      "d15_earned_runs",
      "d30_earned_runs",
      "d7_hits_allowed",
      "d15_hits_allowed",
      "d30_hits_allowed",
      "bvp_at_bats",
      "bvp_hits",
      "bvp_home_runs",
      "bvp_rbi",
      "bvp_strikeouts",
      "bvp_walks",
      "bvp_plate_appearances",
      "line",
      "line_diff"
    ]
  },
  "home_runs": {
    "random_forest": [
      "streak_type_hot",
      "streak_count",
      "hit_streak",
      "win_streak",
      "rolling_result_avg_7",
      "d7_hits",
      "d7_home_runs",
      "d7_rbis",
      "d7_walks",
      "d15_hits",
      "d15_home_runs",
      "d15_rbis",
      "d15_walks",
      "d30_hits",
      "d30_home_runs",
      "d30_rbis",
      "d30_walks",
      "d7_total_bases",
      "d15_total_bases",
      "d30_total_bases",
      "d7_hits_runs_rbis",
      "d15_hits_runs_rbis",
      "d30_hits_runs_rbis",
      "d7_stolen_bases",
      "d15_stolen_bases",
      "d30_stolen_bases",
      "d7_strikeouts_batting",
      "d15_strikeouts_batting",
      "d30_strikeouts_batting",
      "d7_strikeouts_pitching",
      "d15_strikeouts_pitching",
      "d30_strikeouts_pitching",
      "d7_walks_allowed",
      "d15_walks_allowed",
      "d30_walks_allowed",
      "d7_earned_runs",
      "d15_earned_runs",
      "d30_earned_runs",
      "d7_hits_allowed",
      "d15_hits_allowed",
      "d30_hits_allowed",
      "bvp_at_bats",
      "bvp_hits",
      "bvp_home_runs",
      "bvp_rbi",
      "bvp_strikeouts",
      "bvp_walks",
      "bvp_plate_appearances",
      "line_diff"
    ],
    "logistic_regression": [
      "streak_type_hot",
      "streak_count",
      "hit_streak",
      "win_streak",
      "rolling_result_avg_7",
      "d7_hits",
      "d7_home_runs",
      "d7_rbis",
      "d7_walks",
      "d15_hits",
      "d15_home_runs",
      "d15_rbis",
      "d15_walks",
      "d30_hits",
      "d30_home_runs",
      "d30_rbis",
      "d30_walks",
      "d7_total_bases",
      "d15_total_bases",
      "d30_total_bases",
      "d7_hits_runs_rbis",
      "d15_hits_runs_rbis",
      "d30_hits_runs_rbis",
      "d7_stolen_bases",
      "d15_stolen_bases",
      "d30_stolen_bases",
      "d7_strikeouts_batting",
      "d15_strikeouts_batting",
      "d30_strikeouts_batting",
      "d7_strikeouts_pitching",
      "d15_strikeouts_pitching",
      "d30_strikeouts_pitching",
      "d7_walks_allowed",
      "d15_walks_allowed",
      "d30_walks_allowed",
      "d7_earned_runs",
      "d15_earned_runs",
      "d30_earned_runs",
      "d7_hits_allowed",
      "d15_hits_allowed",
      "d30_hits_allowed",
      "bvp_at_bats",
      "bvp_hits",
      "bvp_home_runs",
      "bvp_rbi",
      "bvp_strikeouts",
      "bvp_walks",
      "bvp_plate_appearances",
      "line_diff"
    ]
  },
  "total_bases": {
    "random_forest": [
      "streak_type_hot",
      "streak_type_cold",
      "streak_count",
      "hit_streak",
      "win_streak",
      "rolling_result_avg_7",
      "d7_hits",
      "d7_home_runs",
      "d7_rbis",
      "d7_walks",
      "d15_hits",
      "d15_home_runs",
      "d15_rbis",
      "d15_walks",
      "d30_hits",
      "d30_home_runs",
      "d30_rbis",
      "d30_walks",
      "d7_total_bases",
      "d15_total_bases",
      "d30_total_bases",
      "d7_hits_runs_rbis",
      "d15_hits_runs_rbis",
      "d30_hits_runs_rbis",
      "d7_stolen_bases",
      "d15_stolen_bases",
      "d30_stolen_bases",
      "d7_strikeouts_batting",
      "d15_strikeouts_batting",
      "d30_strikeouts_batting",
      "d7_strikeouts_pitching",
      "d15_strikeouts_pitching",
      "d30_strikeouts_pitching",
      "d7_walks_allowed",
      "d15_walks_allowed",
      "d30_walks_allowed",
      "d7_earned_runs",
      "d15_earned_runs",
      "d30_earned_runs",
      "d7_hits_allowed",
      "d15_hits_allowed",
      "d30_hits_allowed",
      "bvp_at_bats",
      "bvp_hits",
      "bvp_home_runs",
      "bvp_rbi",
      "bvp_strikeouts",
      "bvp_walks",
      "bvp_plate_appearances",
      "line",
      "line_diff"
    ],
    "logistic_regression": [
      "streak_type_hot",
      "streak_type_cold",
      "streak_count",
      "hit_streak",
      "win_streak",
      "rolling_result_avg_7",
      "d7_hits",
      "d7_home_runs",
      "d7_rbis",
      "d7_walks",
      "d15_hits",
      "d15_home_runs",
      "d15_rbis",
      "d15_walks",
      "d30_hits",
      "d30_home_runs",
      "d30_rbis",
      "d30_walks",
      "d7_total_bases",
      "d15_total_bases",
      "d30_total_bases",
      "d7_hits_runs_rbis",
      "d15_hits_runs_rbis",
      "d30_hits_runs_rbis",
      "d7_stolen_bases",
      "d15_stolen_bases",
      "d30_stolen_bases",
      "d7_strikeouts_batting",
      "d15_strikeouts_batting",
      "d30_strikeouts_batting",
      "d7_strikeouts_pitching",
      "d15_strikeouts_pitching",
      "d30_strikeouts_pitching",
      "d7_walks_allowed",
      "d15_walks_allowed",
      "d30_walks_allowed",
      "d7_earned_runs",
      "d15_earned_runs",
      "d30_earned_runs",
      "d7_hits_allowed",
      "d15_hits_allowed",
      "d30_hits_allowed",
      "bvp_at_bats",
      "bvp_hits",
      "bvp_home_runs",
      "bvp_rbi",
      "bvp_strikeouts",
      "bvp_walks",
      "bvp_plate_appearances",
      "line",
      "line_diff"
    ]
  },
  "rbis": {
    "random_forest": [
      "streak_type_hot",
      "streak_type_cold",
      "streak_count",
      "hit_streak",
      "win_streak",
      "rolling_result_avg_7",
      "d7_hits",
      "d7_home_runs",
      "d7_rbis",
      "d7_walks",
      "d15_hits",
      "d15_home_runs",
      "d15_rbis",
      "d15_walks",
      "d30_hits",
      "d30_home_runs",
      "d30_rbis",
      "d30_walks",
      "d7_total_bases",
      "d15_total_bases",
      "d30_total_bases",
      "d7_hits_runs_rbis",
      "d15_hits_runs_rbis",
      "d30_hits_runs_rbis",
      "d7_stolen_bases",
      "d15_stolen_bases",
      "d30_stolen_bases",
      "d7_strikeouts_batting",
      "d15_strikeouts_batting",
      "d30_strikeouts_batting",
      "d7_strikeouts_pitching",
      "d15_strikeouts_pitching",
      "d30_strikeouts_pitching",
      "d7_walks_allowed",
      "d15_walks_allowed",
      "d30_walks_allowed",
      "d7_earned_runs",
      "d15_earned_runs",
      "d30_earned_runs",
      "d7_hits_allowed",
      "d15_hits_allowed",
      "d30_hits_allowed",
      "bvp_at_bats",
      "bvp_hits",
      "bvp_home_runs",
      "bvp_rbi",
      "bvp_strikeouts",
      "bvp_walks",
      "bvp_plate_appearances",
      "line",
      "line_diff"
    ],
    "logistic_regression": [
      "streak_type_hot",
      "streak_type_cold",
      "streak_count",
      "hit_streak",
      "win_streak",
      "rolling_result_avg_7",
      "d7_hits",
      "d7_home_runs",
      "d7_rbis",
      "d7_walks",
      "d15_hits",
      "d15_home_runs",
      "d15_rbis",
      "d15_walks",
      "d30_hits",
      "d30_home_runs",
      "d30_rbis",
      "d30_walks",
      "d7_total_bases",
      "d15_total_bases",
      "d30_total_bases",
      "d7_hits_runs_rbis",
      "d15_hits_runs_rbis",
      "d30_hits_runs_rbis",
      "d7_stolen_bases",
      "d15_stolen_bases",
      "d30_stolen_bases",
      "d7_strikeouts_batting",
      "d15_strikeouts_batting",
      "d30_strikeouts_batting",
      "d7_strikeouts_pitching",
      "d15_strikeouts_pitching",
      "d30_strikeouts_pitching",
      "d7_walks_allowed",
      "d15_walks_allowed",
      "d30_walks_allowed",
      "d7_earned_runs",
      "d15_earned_runs",
      "d30_earned_runs",
      "d7_hits_allowed",
      "d15_hits_allowed",
      "d30_hits_allowed",
      "bvp_at_bats",
      "bvp_hits",
      "bvp_home_runs",
      "bvp_rbi",
      "bvp_strikeouts",
      "bvp_walks",
      "bvp_plate_appearances",
      "line",
      "line_diff"
    ]
  },
  "runs_scored": {
    "random_forest": [
      "streak_type_hot",
      "streak_type_cold",
      "streak_count",
      "hit_streak",
      "win_streak",
      "rolling_result_avg_7",
      "d7_hits",
      "d7_home_runs",
      "d7_rbis",
      "d7_walks",
      "d15_hits",
      "d15_home_runs",
      "d15_rbis",
      "d15_walks",
      "d30_hits",
      "d30_home_runs",
      "d30_rbis",
      "d30_walks",
      "d7_total_bases",
      "d15_total_bases",
      "d30_total_bases",
      "d7_hits_runs_rbis",
      "d15_hits_runs_rbis",
      "d30_hits_runs_rbis",
      "d7_stolen_bases",
      "d15_stolen_bases",
      "d30_stolen_bases",
      "d7_strikeouts_batting",
      "d15_strikeouts_batting",
      "d30_strikeouts_batting",
      "d7_strikeouts_pitching",
      "d15_strikeouts_pitching",
      "d30_strikeouts_pitching",
      "d7_walks_allowed",
      "d15_walks_allowed",
      "d30_walks_allowed",
      "d7_earned_runs",
      "d15_earned_runs",
      "d30_earned_runs",
      "d7_hits_allowed",
      "d15_hits_allowed",
      "d30_hits_allowed",
      "bvp_at_bats",
      "bvp_hits",
      "bvp_home_runs",
      "bvp_rbi",
      "bvp_strikeouts",
      "bvp_walks",
      "bvp_plate_appearances",
      "line",
      "line_diff"
    ],
    "logistic_regression": [
      "streak_type_hot",
      "streak_type_cold",
      "streak_count",
      "hit_streak",
      "win_streak",
      "rolling_result_avg_7",
      "d7_hits",
      "d7_home_runs",
      "d7_rbis",
      "d7_walks",
      "d15_hits",
      "d15_home_runs",
      "d15_rbis",
      "d15_walks",
      "d30_hits",
      "d30_home_runs",
      "d30_rbis",
      "d30_walks",
      "d7_total_bases",
      "d15_total_bases",
      "d30_total_bases",
      "d7_hits_runs_rbis",
      "d15_hits_runs_rbis",
      "d30_hits_runs_rbis",
      "d7_stolen_bases",
      "d15_stolen_bases",
      "d30_stolen_bases",
      "d7_strikeouts_batting",
      "d15_strikeouts_batting",
      "d30_strikeouts_batting",
      "d7_strikeouts_pitching",
      "d15_strikeouts_pitching",
      "d30_strikeouts_pitching",
      "d7_walks_allowed",
      "d15_walks_allowed",
      "d30_walks_allowed",
      "d7_earned_runs",
      "d15_earned_runs",
      "d30_earned_runs",
      "d7_hits_allowed",
      "d15_hits_allowed",
      "d30_hits_allowed",
      "bvp_at_bats",
      "bvp_hits",
      "bvp_home_runs",
      "bvp_rbi",
      "bvp_strikeouts",
      "bvp_walks",
      "bvp_plate_appearances",
      "line",
      "line_diff"
    ]
  },
  "strikeouts_batting": {
    "random_forest": [
      "streak_type_hot",
      "streak_type_cold",
      "streak_count",
      "hit_streak",
      "win_streak",
      "rolling_result_avg_7",
      "d7_hits",
      "d7_home_runs",
      "d7_rbis",
      "d7_walks",
      "d15_hits",
      "d15_home_runs",
      "d15_rbis",
      "d15_walks",
      "d30_hits",
      "d30_home_runs",
      "d30_rbis",
      "d30_walks",
      "d7_total_bases",
      "d15_total_bases",
      "d30_total_bases",
      "d7_hits_runs_rbis",
      "d15_hits_runs_rbis",
      "d30_hits_runs_rbis",
      "d7_stolen_bases",
      "d15_stolen_bases",
      "d30_stolen_bases",
      "d7_strikeouts_batting",
      "d15_strikeouts_batting",
      "d30_strikeouts_batting",
      "d7_strikeouts_pitching",
      "d15_strikeouts_pitching",
      "d30_strikeouts_pitching",
      "d7_walks_allowed",
      "d15_walks_allowed",
      "d30_walks_allowed",
      "d7_earned_runs",
      "d15_earned_runs",
      "d30_earned_runs",
      "d7_hits_allowed",
      "d15_hits_allowed",
      "d30_hits_allowed",
      "bvp_at_bats",
      "bvp_hits",
      "bvp_home_runs",
      "bvp_rbi",
      "bvp_strikeouts",
      "bvp_walks",
      "bvp_plate_appearances",
      "line",
      "line_diff"
    ],
    "logistic_regression": [
      "streak_type_hot",
      "streak_type_cold",
      "streak_count",
      "hit_streak",
      "win_streak",
      "rolling_result_avg_7",
      "d7_hits",
      "d7_home_runs",
      "d7_rbis",
      "d7_walks",
      "d15_hits",
      "d15_home_runs",
      "d15_rbis",
      "d15_walks",
      "d30_hits",
      "d30_home_runs",
      "d30_rbis",
      "d30_walks",
      "d7_total_bases",
      "d15_total_bases",
      "d30_total_bases",
      "d7_hits_runs_rbis",
      "d15_hits_runs_rbis",
      "d30_hits_runs_rbis",
      "d7_stolen_bases",
      "d15_stolen_bases",
      "d30_stolen_bases",
      "d7_strikeouts_batting",
      "d15_strikeouts_batting",
      "d30_strikeouts_batting",
      "d7_strikeouts_pitching",
      "d15_strikeouts_pitching",
      "d30_strikeouts_pitching",
      "d7_walks_allowed",
      "d15_walks_allowed",
      "d30_walks_allowed",
      "d7_earned_runs",
      "d15_earned_runs",
      "d30_earned_runs",
      "d7_hits_allowed",
      "d15_hits_allowed",
      "d30_hits_allowed",
      "bvp_at_bats",
      "bvp_hits",
      "bvp_home_runs",
      "bvp_rbi",
      "bvp_strikeouts",
      "bvp_walks",
      "bvp_plate_appearances",
      "line",
      "line_diff"
    ]
  },
  "walks": {
    "random_forest": [
      "streak_type_hot",
      "streak_type_cold",
      "streak_count",
      "rolling_result_avg_7",
      "d7_hits",
      "d7_home_runs",
      "d7_rbis",
      "d7_walks",
      "d15_hits",
      "d15_home_runs",
      "d15_rbis",
      "d15_walks",
      "d30_hits",
      "d30_home_runs",
      "d30_rbis",
      "d30_walks",
      "d7_total_bases",
      "d15_total_bases",
      "d30_total_bases",
      "d7_hits_runs_rbis",
      "d15_hits_runs_rbis",
      "d30_hits_runs_rbis",
      "d7_stolen_bases",
      "d15_stolen_bases",
      "d30_stolen_bases",
      "d7_strikeouts_batting",
      "d15_strikeouts_batting",
      "d30_strikeouts_batting",
      "d7_strikeouts_pitching",
      "d15_strikeouts_pitching",
      "d30_strikeouts_pitching",
      "d7_walks_allowed",
      "d15_walks_allowed",
      "d30_walks_allowed",
      "d7_earned_runs",
      "d15_earned_runs",
      "d30_earned_runs",
      "d7_hits_allowed",
      "d15_hits_allowed",
      "d30_hits_allowed",
      "bvp_at_bats",
      "bvp_hits",
      "bvp_home_runs",
      "bvp_rbi",
      "bvp_strikeouts",
      "bvp_walks",
      "bvp_plate_appearances",
      "line",
      "line_diff"
    ],
    "logistic_regression": [
      "streak_type_hot",
      "streak_type_cold",
      "streak_count",
      "rolling_result_avg_7",
      "d7_hits",
      "d7_home_runs",
      "d7_rbis",
      "d7_walks",
      "d15_hits",
      "d15_home_runs",
      "d15_rbis",
      "d15_walks",
      "d30_hits",
      "d30_home_runs",
      "d30_rbis",
      "d30_walks",
      "d7_total_bases",
      "d15_total_bases",
      "d30_total_bases",
      "d7_hits_runs_rbis",
      "d15_hits_runs_rbis",
      "d30_hits_runs_rbis",
      "d7_stolen_bases",
      "d15_stolen_bases",
      "d30_stolen_bases",
      "d7_strikeouts_batting",
      "d15_strikeouts_batting",
      "d30_strikeouts_batting",
      "d7_strikeouts_pitching",
      "d15_strikeouts_pitching",
      "d30_strikeouts_pitching",
      "d7_walks_allowed",
      "d15_walks_allowed",
      "d30_walks_allowed",
      "d7_earned_runs",
      "d15_earned_runs",
      "d30_earned_runs",
      "d7_hits_allowed",
      "d15_hits_allowed",
      "d30_hits_allowed",
      "bvp_at_bats",
      "bvp_hits",
      "bvp_home_runs",
      "bvp_rbi",
      "bvp_strikeouts",
      "bvp_walks",
      "bvp_plate_appearances",
      "line",
      "line_diff"
    ]
  },
  "stolen_bases": {
    "random_forest": [
      "streak_type_hot",
      "streak_type_cold",
      "streak_count",
      "rolling_result_avg_7",
      "d7_hits",
      "d7_home_runs",
      "d7_rbis",
      "d7_walks",
      "d15_hits",
      "d15_home_runs",
      "d15_rbis",
      "d15_walks",
      "d30_hits",
      "d30_home_runs",
      "d30_rbis",
      "d30_walks",
      "d7_total_bases",
      "d15_total_bases",
      "d30_total_bases",
      "d7_hits_runs_rbis",
      "d15_hits_runs_rbis",
      "d30_hits_runs_rbis",
      "d7_stolen_bases",
      "d15_stolen_bases",
      "d30_stolen_bases",
      "d7_strikeouts_batting",
      "d15_strikeouts_batting",
      "d30_strikeouts_batting",
      "d7_strikeouts_pitching",
      "d15_strikeouts_pitching",
      "d30_strikeouts_pitching",
      "d7_walks_allowed",
      "d15_walks_allowed",
      "d30_walks_allowed",
      "d7_hits_allowed",
      "d15_hits_allowed",
      "d30_hits_allowed",
      "bvp_at_bats",
      "bvp_hits",
      "bvp_home_runs",
      "bvp_rbi",
      "bvp_strikeouts",
      "bvp_walks",
      "bvp_plate_appearances",
      "line_diff"
    ],
    "logistic_regression": [
      "streak_type_hot",
      "streak_type_cold",
      "streak_count",
      "rolling_result_avg_7",
      "d7_hits",
      "d7_home_runs",
      "d7_rbis",
      "d7_walks",
      "d15_hits",
      "d15_home_runs",
      "d15_rbis",
      "d15_walks",
      "d30_hits",
      "d30_home_runs",
      "d30_rbis",
      "d30_walks",
      "d7_total_bases",
      "d15_total_bases",
      "d30_total_bases",
      "d7_hits_runs_rbis",
      "d15_hits_runs_rbis",
      "d30_hits_runs_rbis",
      "d7_stolen_bases",
      "d15_stolen_bases",
      "d30_stolen_bases",
      "d7_strikeouts_batting",
      "d15_strikeouts_batting",
      "d30_strikeouts_batting",
      "d7_strikeouts_pitching",
      "d15_strikeouts_pitching",
      "d30_strikeouts_pitching",
      "d7_walks_allowed",
      "d15_walks_allowed",
      "d30_walks_allowed",
      "d7_hits_allowed",
      "d15_hits_allowed",
      "d30_hits_allowed",
      "bvp_at_bats",
      "bvp_hits",
      "bvp_home_runs",
      "bvp_rbi",
      "bvp_strikeouts",
      "bvp_walks",
      "bvp_plate_appearances",
      "line_diff"
    ]
  },
  "strikeouts_pitching": {
    "random_forest": [
      "streak_type_hot",
      "streak_type_cold",
      "streak_count",
      "hit_streak",
      "win_streak",
      "rolling_result_avg_7",
      "d7_hits",
      "d7_home_runs",
      "d7_rbis",
      "d7_walks",
      "d15_hits",
      "d15_home_runs",
      "d15_rbis",
      "d15_walks",
      "d30_hits",
      "d30_home_runs",
      "d30_rbis",
      "d30_walks",
      "d7_total_bases",
      "d15_total_bases",
      "d30_total_bases",
      "d7_hits_runs_rbis",
      "d15_hits_runs_rbis",
      "d30_hits_runs_rbis",
      "d7_stolen_bases",
      "d15_stolen_bases",
      "d30_stolen_bases",
      "d7_strikeouts_batting",
      "d15_strikeouts_batting",
      "d30_strikeouts_batting",
      "d7_strikeouts_pitching",
      "d15_strikeouts_pitching",
      "d30_strikeouts_pitching",
      "d7_walks_allowed",
      "d15_walks_allowed",
      "d30_walks_allowed",
      "d7_earned_runs",
      "d15_earned_runs",
      "d30_earned_runs",
      "d7_hits_allowed",
      "d15_hits_allowed",
      "d30_hits_allowed",
      "bvp_at_bats",
      "bvp_strikeouts",
      "bvp_walks",
      "bvp_plate_appearances",
      "line",
      "line_diff"
    ],
    "logistic_regression": [
      "streak_type_hot",
      "streak_type_cold",
      "streak_count",
      "hit_streak",
      "win_streak",
      "rolling_result_avg_7",
      "d7_hits",
      "d7_home_runs",
      "d7_rbis",
      "d7_walks",
      "d15_hits",
      "d15_home_runs",
      "d15_rbis",
      "d15_walks",
      "d30_hits",
      "d30_home_runs",
      "d30_rbis",
      "d30_walks",
      "d7_total_bases",
      "d15_total_bases",
      "d30_total_bases",
      "d7_hits_runs_rbis",
      "d15_hits_runs_rbis",
      "d30_hits_runs_rbis",
      "d7_stolen_bases",
      "d15_stolen_bases",
      "d30_stolen_bases",
      "d7_strikeouts_batting",
      "d15_strikeouts_batting",
      "d30_strikeouts_batting",
      "d7_strikeouts_pitching",
      "d15_strikeouts_pitching",
      "d30_strikeouts_pitching",
      "d7_walks_allowed",
      "d15_walks_allowed",
      "d30_walks_allowed",
      "d7_earned_runs",
      "d15_earned_runs",
      "d30_earned_runs",
      "d7_hits_allowed",
      "d15_hits_allowed",
      "d30_hits_allowed",
      "bvp_at_bats",
      "bvp_strikeouts",
      "bvp_walks",
      "bvp_plate_appearances",
      "line",
      "line_diff"
    ]
  },
  "walks_allowed": {
    "random_forest": [
      "streak_type_hot",
      "streak_type_cold",
      "streak_count",
      "hit_streak",
      "win_streak",
      "rolling_result_avg_7",
      "d7_hits",
      "d7_home_runs",
      "d7_rbis",
      "d7_walks",
      "d15_hits",
      "d15_home_runs",
      "d15_rbis",
      "d15_walks",
      "d30_hits",
      "d30_home_runs",
      "d30_rbis",
      "d30_walks",
      "d7_total_bases",
      "d15_total_bases",
      "d30_total_bases",
      "d7_hits_runs_rbis",
      "d15_hits_runs_rbis",
      "d30_hits_runs_rbis",
      "d7_stolen_bases",
      "d15_stolen_bases",
      "d30_stolen_bases",
      "d7_strikeouts_batting",
      "d15_strikeouts_batting",
      "d30_strikeouts_batting",
      "d7_strikeouts_pitching",
      "d15_strikeouts_pitching",
      "d30_strikeouts_pitching",
      "d7_walks_allowed",
      "d15_walks_allowed",
      "d30_walks_allowed",
      "d7_earned_runs",
      "d15_earned_runs",
      "d30_earned_runs",
      "d7_hits_allowed",
      "d15_hits_allowed",
      "d30_hits_allowed",
      "bvp_at_bats",
      "bvp_strikeouts",
      "bvp_plate_appearances",
      "line",
      "line_diff"
    ],
    "logistic_regression": [
      "streak_type_hot",
      "streak_type_cold",
      "streak_count",
      "hit_streak",
      "win_streak",
      "rolling_result_avg_7",
      "d7_hits",
      "d7_home_runs",
      "d7_rbis",
      "d7_walks",
      "d15_hits",
      "d15_home_runs",
      "d15_rbis",
      "d15_walks",
      "d30_hits",
      "d30_home_runs",
      "d30_rbis",
      "d30_walks",
      "d7_total_bases",
      "d15_total_bases",
      "d30_total_bases",
      "d7_hits_runs_rbis",
      "d15_hits_runs_rbis",
      "d30_hits_runs_rbis",
      "d7_stolen_bases",
      "d15_stolen_bases",
      "d30_stolen_bases",
      "d7_strikeouts_batting",
      "d15_strikeouts_batting",
      "d30_strikeouts_batting",
      "d7_strikeouts_pitching",
      "d15_strikeouts_pitching",
      "d30_strikeouts_pitching",
      "d7_walks_allowed",
      "d15_walks_allowed",
      "d30_walks_allowed",
      "d7_earned_runs",
      "d15_earned_runs",
      "d30_earned_runs",
      "d7_hits_allowed",
      "d15_hits_allowed",
      "d30_hits_allowed",
      "bvp_at_bats",
      "bvp_strikeouts",
      "bvp_plate_appearances",
      "line",
      "line_diff"
    ]
  },
  "earned_runs": {
    "random_forest": [
      "streak_type_hot",
      "streak_type_cold",
      "streak_count",
      "rolling_result_avg_7",
      "d7_hits",
      "d7_home_runs",
      "d7_rbis",
      "d7_walks",
      "d15_hits",
      "d15_home_runs",
      "d15_rbis",
      "d15_walks",
      "d30_hits",
      "d30_home_runs",
      "d30_rbis",
      "d30_walks",
      "d7_total_bases",
      "d15_total_bases",
      "d30_total_bases",
      "d7_hits_runs_rbis",
      "d15_hits_runs_rbis",
      "d30_hits_runs_rbis",
      "d7_stolen_bases",
      "d15_stolen_bases",
      "d30_stolen_bases",
      "d7_strikeouts_batting",
      "d15_strikeouts_batting",
      "d30_strikeouts_batting",
      "d7_strikeouts_pitching",
      "d15_strikeouts_pitching",
      "d30_strikeouts_pitching",
      "d7_walks_allowed",
      "d15_walks_allowed",
      "d30_walks_allowed",
      "d7_earned_runs",
      "d15_earned_runs",
      "d30_earned_runs",
      "d7_hits_allowed",
      "d15_hits_allowed",
      "d30_hits_allowed",
      "bvp_at_bats",
      "bvp_strikeouts",
      "bvp_plate_appearances",
      "line",
      "line_diff"
    ],
    "logistic_regression": [
      "streak_type_hot",
      "streak_type_cold",
      "streak_count",
      "rolling_result_avg_7",
      "d7_hits",
      "d7_home_runs",
      "d7_rbis",
      "d7_walks",
      "d15_hits",
      "d15_home_runs",
      "d15_rbis",
      "d15_walks",
      "d30_hits",
      "d30_home_runs",
      "d30_rbis",
      "d30_walks",
      "d7_total_bases",
      "d15_total_bases",
      "d30_total_bases",
      "d7_hits_runs_rbis",
      "d15_hits_runs_rbis",
      "d30_hits_runs_rbis",
      "d7_stolen_bases",
      "d15_stolen_bases",
      "d30_stolen_bases",
      "d7_strikeouts_batting",
      "d15_strikeouts_batting",
      "d30_strikeouts_batting",
      "d7_strikeouts_pitching",
      "d15_strikeouts_pitching",
      "d30_strikeouts_pitching",
      "d7_walks_allowed",
      "d15_walks_allowed",
      "d30_walks_allowed",
      "d7_earned_runs",
      "d15_earned_runs",
      "d30_earned_runs",
      "d7_hits_allowed",
      "d15_hits_allowed",
      "d30_hits_allowed",
      "bvp_at_bats",
      "bvp_strikeouts",
      "bvp_plate_appearances",
      "line",
      "line_diff"
    ]
  },
  "outs_recorded": {
    "random_forest": [
      "streak_type_hot",
      "streak_type_cold",
      "streak_count",
      "hit_streak",
      "win_streak",
      "rolling_result_avg_7",
      "d7_hits",
      "d7_rbis",
      "d15_hits",
      "d15_rbis",
      "d30_hits",
      "d30_rbis",
      "d7_total_bases",
      "d15_total_bases",
      "d30_total_bases",
      "d7_hits_runs_rbis",
      "d15_hits_runs_rbis",
      "d30_hits_runs_rbis",
      "d7_strikeouts_pitching",
      "d15_strikeouts_pitching",
      "d30_strikeouts_pitching",
      "d7_walks_allowed",
      "d15_walks_allowed",
      "d30_walks_allowed",
      "d7_earned_runs",
      "d15_earned_runs",
      "d30_earned_runs",
      "d7_hits_allowed",
      "d15_hits_allowed",
      "d30_hits_allowed",
      "bvp_at_bats",
      "bvp_strikeouts",
      "bvp_plate_appearances",
      "line",
      "line_diff"
    ],
    "logistic_regression": [
      "streak_type_hot",
      "streak_type_cold",
      "streak_count",
      "hit_streak",
      "win_streak",
      "rolling_result_avg_7",
      "d7_hits",
      "d7_rbis",
      "d15_hits",
      "d15_rbis",
      "d30_hits",
      "d30_rbis",
      "d7_total_bases",
      "d15_total_bases",
      "d30_total_bases",
      "d7_hits_runs_rbis",
      "d15_hits_runs_rbis",
      "d30_hits_runs_rbis",
      "d7_strikeouts_pitching",
      "d15_strikeouts_pitching",
      "d30_strikeouts_pitching",
      "d7_walks_allowed",
      "d15_walks_allowed",
      "d30_walks_allowed",
      "d7_earned_runs",
      "d15_earned_runs",
      "d30_earned_runs",
      "d7_hits_allowed",
      "d15_hits_allowed",
      "d30_hits_allowed",
      "bvp_at_bats",
      "bvp_strikeouts",
      "bvp_plate_appearances",
      "line",
      "line_diff"
    ]
  },
  "hits_allowed": {
    "random_forest": [
      "streak_type_hot",
      "streak_type_cold",
      "streak_count",
      "rolling_result_avg_7",
      "d7_hits",
      "d7_home_runs",
      "d7_rbis",
      "d7_walks",
      "d15_hits",
      "d15_home_runs",
      "d15_rbis",
      "d15_walks",
      "d30_hits",
      "d30_home_runs",
      "d30_rbis",
      "d30_walks",
      "d7_total_bases",
      "d15_total_bases",
      "d30_total_bases",
      "d7_hits_runs_rbis",
      "d15_hits_runs_rbis",
      "d30_hits_runs_rbis",
      "d7_stolen_bases",
      "d15_stolen_bases",
      "d30_stolen_bases",
      "d7_strikeouts_batting",
      "d15_strikeouts_batting",
      "d30_strikeouts_batting",
      "d7_strikeouts_pitching",
      "d15_strikeouts_pitching",
      "d30_strikeouts_pitching",
      "d7_walks_allowed",
      "d15_walks_allowed",
      "d30_walks_allowed",
      "d7_earned_runs",
      "d15_earned_runs",
      "d30_earned_runs",
      "d7_hits_allowed",
      "d15_hits_allowed",
      "d30_hits_allowed",
      "bvp_at_bats",
      "bvp_strikeouts",
      "bvp_plate_appearances",
      "line",
      "line_diff"
    ],
    "logistic_regression": [
      "streak_type_hot",
      "streak_type_cold",
      "streak_count",
      "rolling_result_avg_7",
      "d7_hits",
      "d7_home_runs",
      "d7_rbis",
      "d7_walks",
      "d15_hits",
      "d15_home_runs",
      "d15_rbis",
      "d15_walks",
      "d30_hits",
      "d30_home_runs",
      "d30_rbis",
      "d30_walks",
      "d7_total_bases",
      "d15_total_bases",
      "d30_total_bases",
      "d7_hits_runs_rbis",
      "d15_hits_runs_rbis",
      "d30_hits_runs_rbis",
      "d7_stolen_bases",
      "d15_stolen_bases",
      "d30_stolen_bases",
      "d7_strikeouts_batting",
      "d15_strikeouts_batting",
      "d30_strikeouts_batting",
      "d7_strikeouts_pitching",
      "d15_strikeouts_pitching",
      "d30_strikeouts_pitching",
      "d7_walks_allowed",
      "d15_walks_allowed",
      "d30_walks_allowed",
      "d7_earned_runs",
      "d15_earned_runs",
      "d30_earned_runs",
      "d7_hits_allowed",
      "d15_hits_allowed",
      "d30_hits_allowed",
      "bvp_at_bats",
      "bvp_strikeouts",
      "bvp_plate_appearances",
      "line",
      "line_diff"
    ]
  },
  "hits_runs_rbis": {
    "random_forest": [
      "streak_type_hot",
      "streak_type_cold",
      "streak_count",
      "hit_streak",
      "win_streak",
      "rolling_result_avg_7",
      "d7_hits",
      "d7_home_runs",
      "d7_rbis",
      "d7_walks",
      "d15_hits",
      "d15_home_runs",
      "d15_rbis",
      "d15_walks",
      "d30_hits",
      "d30_home_runs",
      "d30_rbis",
      "d30_walks",
      "d7_total_bases",
      "d15_total_bases",
      "d30_total_bases",
      "d7_hits_runs_rbis",
      "d15_hits_runs_rbis",
      "d30_hits_runs_rbis",
      "d7_stolen_bases",
      "d15_stolen_bases",
      "d30_stolen_bases",
      "d7_strikeouts_batting",
      "d15_strikeouts_batting",
      "d30_strikeouts_batting",
      "d7_strikeouts_pitching",
      "d15_strikeouts_pitching",
      "d30_strikeouts_pitching",
      "d7_walks_allowed",
      "d15_walks_allowed",
      "d30_walks_allowed",
      "d7_earned_runs",
      "d15_earned_runs",
      "d30_earned_runs",
      "d7_hits_allowed",
      "d15_hits_allowed",
      "d30_hits_allowed",
      "bvp_at_bats",
      "bvp_hits",
      "bvp_home_runs",
      "bvp_rbi",
      "bvp_strikeouts",
      "bvp_walks",
      "bvp_plate_appearances",
      "line",
      "line_diff"
    ],
    "logistic_regression": [
      "streak_type_hot",
      "streak_type_cold",
      "streak_count",
      "hit_streak",
      "win_streak",
      "rolling_result_avg_7",
      "d7_hits",
      "d7_home_runs",
      "d7_rbis",
      "d7_walks",
      "d15_hits",
      "d15_home_runs",
      "d15_rbis",
      "d15_walks",
      "d30_hits",
      "d30_home_runs",
      "d30_rbis",
      "d30_walks",
      "d7_total_bases",
      "d15_total_bases",
      "d30_total_bases",
      "d7_hits_runs_rbis",
      "d15_hits_runs_rbis",
      "d30_hits_runs_rbis",
      "d7_stolen_bases",
      "d15_stolen_bases",
      "d30_stolen_bases",
      "d7_strikeouts_batting",
      "d15_strikeouts_batting",
      "d30_strikeouts_batting",
      "d7_strikeouts_pitching",
      "d15_strikeouts_pitching",
      "d30_strikeouts_pitching",
      "d7_walks_allowed",
      "d15_walks_allowed",
      "d30_walks_allowed",
      "d7_earned_runs",
      "d15_earned_runs",
      "d30_earned_runs",
      "d7_hits_allowed",
      "d15_hits_allowed",
      "d30_hits_allowed",
      "bvp_at_bats",
      "bvp_hits",
      "bvp_home_runs",
      "bvp_rbi",
      "bvp_strikeouts",
      "bvp_walks",
      "bvp_plate_appearances",
      "line",
      "line_diff"
    ]
  },
  "runs_rbis": {
    "random_forest": [
      "streak_type_hot",
      "streak_type_cold",
      "streak_count",
      "hit_streak",
      "win_streak",
      "rolling_result_avg_7",
      "d7_hits",
      "d7_home_runs",
      "d7_rbis",
      "d7_walks",
      "d15_hits",
      "d15_home_runs",
      "d15_rbis",
      "d15_walks",
      "d30_hits",
      "d30_home_runs",
      "d30_rbis",
      "d30_walks",
      "d7_total_bases",
      "d15_total_bases",
      "d30_total_bases",
      "d7_hits_runs_rbis",
      "d15_hits_runs_rbis",
      "d30_hits_runs_rbis",
      "d7_stolen_bases",
      "d15_stolen_bases",
      "d30_stolen_bases",
      "d7_strikeouts_batting",
      "d15_strikeouts_batting",
      "d30_strikeouts_batting",
      "d7_strikeouts_pitching",
      "d15_strikeouts_pitching",
      "d30_strikeouts_pitching",
      "d7_walks_allowed",
      "d15_walks_allowed",
      "d30_walks_allowed",
      "d7_earned_runs",
      "d15_earned_runs",
      "d30_earned_runs",
      "d7_hits_allowed",
      "d15_hits_allowed",
      "d30_hits_allowed",
      "bvp_at_bats",
      "bvp_hits",
      "bvp_home_runs",
      "bvp_rbi",
      "bvp_strikeouts",
      "bvp_walks",
      "bvp_plate_appearances",
      "line",
      "line_diff"
    ],
    "logistic_regression": [
      "streak_type_hot",
      "streak_type_cold",
      "streak_count",
      "hit_streak",
      "win_streak",
      "rolling_result_avg_7",
      "d7_hits",
      "d7_home_runs",
      "d7_rbis",
      "d7_walks",
      "d15_hits",
      "d15_home_runs",
      "d15_rbis",
      "d15_walks",
      "d30_hits",
      "d30_home_runs",
      "d30_rbis",
      "d30_walks",
      "d7_total_bases",
      "d15_total_bases",
      "d30_total_bases",
      "d7_hits_runs_rbis",
      "d15_hits_runs_rbis",
      "d30_hits_runs_rbis",
      "d7_stolen_bases",
      "d15_stolen_bases",
      "d30_stolen_bases",
      "d7_strikeouts_batting",
      "d15_strikeouts_batting",
      "d30_strikeouts_batting",
      "d7_strikeouts_pitching",
      "d15_strikeouts_pitching",
      "d30_strikeouts_pitching",
      "d7_walks_allowed",
      "d15_walks_allowed",
      "d30_walks_allowed",
      "d7_earned_runs",
      "d15_earned_runs",
      "d30_earned_runs",
      "d7_hits_allowed",
      "d15_hits_allowed",
      "d30_hits_allowed",
      "bvp_at_bats",
      "bvp_hits",
      "bvp_home_runs",
      "bvp_rbi",
      "bvp_strikeouts",
      "bvp_walks",
      "bvp_plate_appearances",
      "line",
      "line_diff"
    ]
  }
}
